simple_proxy_rotator/__init__.py
simple_proxy_rotator/proxy_rotator.py
simple_proxy_rotator-0.0.1.dist-info/METADATA
simple_proxy_rotator-0.0.1.dist-info/WHEEL
simple_proxy_rotator-0.0.1.dist-info/licenses/LICENCE
simple_proxy_rotator-0.0.1.dist-info/RECORD
