Metadata-Version: 2.4
Name: simple-proxy-rotator
Version: 0.0.1
Summary: A library to provide easy to use weighted proxy rotation and Proxy class to manage all of your proxies.
Project-URL: Example usage 1 RU, https://timthewebmaster.com/ru/tools/kinopoisk-parser/
Project-URL: Example usage 1 EN, https://timthewebmaster.com/en/tools/kinopoisk-parser/
Project-URL: Example usage 2 RU, https://timthewebmaster.com/ru/tools/wildberries-scraper/
Project-URL: Example usage 2 EN, https://timthewebmaster.com/en/tools/wildberries-scraper/
Author-email: Tim The Webmaster <timachuduk@gmail.com>
License-Expression: MIT
License-File: LICENCE
Keywords: proxies,proxy,proxy rotator,proxy swapping,proxy with requests library,proxy with selenium library,weighted proxy rotator
Classifier: Development Status :: 3 - Alpha
Classifier: Environment :: Plugins
Classifier: Intended Audience :: Developers
Classifier: License :: OSI Approved :: GNU General Public License v3 (GPLv3)
Classifier: Natural Language :: English
Classifier: Natural Language :: Russian
Classifier: Operating System :: OS Independent
Classifier: Programming Language :: Python :: 3
Classifier: Topic :: Desktop Environment
Classifier: Topic :: Internet
Classifier: Topic :: Internet :: WWW/HTTP :: Browsers
Classifier: Topic :: Software Development :: Libraries
Classifier: Topic :: Terminals
Classifier: Topic :: Utilities
Requires-Python: >=3.10
